<?xml version="1.0" encoding="UTF-8" standalone="no"?>
<recordset table="format">
  <record id="syslanguage=&quot;en&quot; and name=&quot;chm.cm3r.km.g&quot;" recordid="en - chm.cm3r.km.g">
    <name mandatory="true" type="string">chm.cm3r.km.g</name>
    <field sctype="array">
      <field sctype="structure">
        <flags type="decimal">4096</flags>
        <line type="decimal">1</line>
        <column type="decimal">1</column>
        <length type="decimal">113</length>
        <window type="decimal">0</window>
        <attribute NullValue="1" type="decimal"/>
        <graph sctype="array"/>
        <input NullValue="1" type="string"/>
        <output type="string">Change Details</output>
        <format NullValue="1" type="string"/>
        <property type="string">Frame;ArrayLength=0	canCollapse=0	?Visible=	floatGroup=1	Height=48	Name=	isExpanded=1	Width=225	X=0	Y=0	Caption=Change Details		</property>
      </field>
      <field sctype="structure">
        <flags type="decimal">0</flags>
        <line type="decimal">1</line>
        <column type="decimal">1</column>
        <length type="decimal">113</length>
        <window type="decimal">0</window>
        <attribute NullValue="1" type="decimal"/>
        <graph sctype="array"/>
        <input NullValue="1" type="string"/>
        <output type="string">VO</output>
        <format NullValue="1" type="string"/>
        <property type="string">Label;backGroundStyle=underline	BackColor=12	Bold=1	?BackColor=	?Caption=[$change.caption]	?Italic=	FontIncrease=3	ForeColor=10	headingLevel=h2	Height=2	Name=	Width=225			X=0	Y=0		</property>
      </field>
      <field sctype="structure">
        <flags type="decimal">0</flags>
        <line type="decimal">2</line>
        <column type="decimal">1</column>
        <length type="decimal">23</length>
        <window type="decimal">0</window>
        <attribute NullValue="1" type="decimal"/>
        <graph sctype="array"/>
        <input NullValue="1" type="string"/>
        <output type="string">Change ID</output>
        <format NullValue="1" type="string"/>
        <property type="string">Label;Caption=Change ID	Justification=1	ForeColor=0	Height=2	Name=	Width=45			X=0	Y=3		</property>
      </field>
      <field sctype="structure">
        <flags type="decimal">4</flags>
        <line type="decimal">2</line>
        <column type="decimal">24</column>
        <length type="decimal">30</length>
        <window type="decimal">0</window>
        <attribute NullValue="1" type="decimal"/>
        <graph sctype="array"/>
        <input type="string">number</input>
        <output NullValue="1" type="string"/>
        <format NullValue="1" type="string"/>
        <property type="string">Text;Height=2	Name=	ReadOnly=1	TabStop=	Width=59			X=46	Y=3		Input=number	</property>
      </field>
      <field sctype="structure">
        <flags type="decimal">0</flags>
        <line type="decimal">2</line>
        <column type="decimal">59</column>
        <length type="decimal">17</length>
        <window type="decimal">0</window>
        <attribute NullValue="1" type="decimal"/>
        <graph sctype="array"/>
        <input NullValue="1" type="string"/>
        <output type="string">Assignee</output>
        <format NullValue="1" type="string"/>
        <property type="string">Label;Caption=Assignee	Justification=1	ForeColor=0	Height=2	Name=	Width=33			X=117	Y=3		</property>
      </field>
      <field sctype="structure">
        <flags type="decimal">0</flags>
        <line type="decimal">2</line>
        <column type="decimal">76</column>
        <length type="decimal">30</length>
        <window type="decimal">1</window>
        <attribute NullValue="1" type="decimal"/>
        <graph sctype="array"/>
        <input type="string">assigned.to</input>
        <output NullValue="1" type="string"/>
        <format NullValue="1" type="string"/>
        <property type="string">ComFill;ArrayLength=1	autocomplete=1	Height=2	Name=	FillButtonID=108	ThirdButtonID=10	ReadOnly=0	ComboButtonVisible=0	FillButtonVisible=1	ThirdButtonVisible=0	SelectOnly=1	Width=59			X=151	Y=3		Input=assigned.to	</property>
      </field>
      <field sctype="structure">
        <flags type="decimal">0</flags>
        <line type="decimal">3</line>
        <column type="decimal">1</column>
        <length type="decimal">23</length>
        <window type="decimal">0</window>
        <attribute NullValue="1" type="decimal"/>
        <graph sctype="array"/>
        <input NullValue="1" type="string"/>
        <output type="string">Phase</output>
        <format NullValue="1" type="string"/>
        <property type="string">Label;Caption=Phase	Justification=1	ForeColor=0	Height=2	Name=	Width=45			X=0	Y=5		</property>
      </field>
      <field sctype="structure">
        <flags type="decimal">4</flags>
        <line type="decimal">3</line>
        <column type="decimal">24</column>
        <length type="decimal">30</length>
        <window type="decimal">1</window>
        <attribute NullValue="1" type="decimal"/>
        <graph sctype="array"/>
        <input type="string">current.phase</input>
        <output NullValue="1" type="string"/>
        <format NullValue="1" type="string"/>
        <property type="string">ComFill;ButtonBitmap=10	ArrayLength=1	Height=2	Name=	FillButtonID=9	ThirdButtonID=8	Mandatory=0	ReadOnly=1	ComboButtonVisible=0	FillButtonBitmap=10	FillButtonVisible=0	TabStop=	Width=59			X=46	Y=5		Input=current.phase	DisplayList=$G.chmWfPhases.local	ValueList=$G.chmWfPhases	</property>
      </field>
      <field sctype="structure">
        <flags type="decimal">0</flags>
        <line type="decimal">3</line>
        <column type="decimal">59</column>
        <length type="decimal">17</length>
        <window type="decimal">0</window>
        <attribute NullValue="1" type="decimal"/>
        <graph sctype="array"/>
        <input NullValue="1" type="string"/>
        <output type="string">Phone</output>
        <format NullValue="1" type="string"/>
        <property type="string">Label;Caption=Phone	Justification=1	ForeColor=0	Height=2	Name=	Width=33			X=117	Y=5		</property>
      </field>
      <field sctype="structure">
        <flags type="decimal">0</flags>
        <line type="decimal">3</line>
        <column type="decimal">76</column>
        <length type="decimal">30</length>
        <window type="decimal">0</window>
        <attribute NullValue="1" type="decimal"/>
        <graph sctype="array"/>
        <input type="string">assign.phone</input>
        <output NullValue="1" type="string"/>
        <format NullValue="1" type="string"/>
        <property type="string">Text;Height=2	Name=	Width=59			X=151	Y=5		Input=assign.phone	</property>
      </field>
      <field sctype="structure">
        <flags type="decimal">0</flags>
        <line type="decimal">4</line>
        <column type="decimal">1</column>
        <length type="decimal">23</length>
        <window type="decimal">0</window>
        <attribute NullValue="1" type="decimal"/>
        <graph sctype="array"/>
        <input NullValue="1" type="string"/>
        <output type="string">Status</output>
        <format NullValue="1" type="string"/>
        <property type="string">Label;Caption=Status	Justification=1	Height=2	Name=	Width=45			X=0	Y=7		</property>
      </field>
      <field sctype="structure">
        <flags type="decimal">4</flags>
        <line type="decimal">4</line>
        <column type="decimal">24</column>
        <length type="decimal">30</length>
        <window type="decimal">1</window>
        <attribute NullValue="1" type="decimal"/>
        <graph sctype="array"/>
        <input type="string">status</input>
        <output NullValue="1" type="string"/>
        <format NullValue="1" type="string"/>
        <property type="string">ComFill;BoxLines=5	ArrayLength=1	?Caption=	?ReadOnly=	Height=2	Name=	FillButtonID=9	ThirdButtonID=8	Mandatory=0	ReadOnly=1	ComboButtonVisible=0	FillButtonVisible=0	SelectOnly=1	TabStop=	Visible=1	Width=59			X=46	Y=7		Input=status	DisplayList=$G.cm.status.local	ValueList=$G.cm.status	</property>
      </field>
      <field sctype="structure">
        <flags type="decimal">0</flags>
        <line type="decimal">4</line>
        <column type="decimal">59</column>
        <length type="decimal">17</length>
        <window type="decimal">0</window>
        <attribute NullValue="1" type="decimal"/>
        <graph sctype="array"/>
        <input NullValue="1" type="string"/>
        <output type="string">Assigned On</output>
        <format NullValue="1" type="string"/>
        <property type="string">Label;Caption=Assigned On	Justification=1	?Caption=	ForeColor=0	Height=2	Name=	Width=33			X=117	Y=7		</property>
      </field>
      <field sctype="structure">
        <flags type="decimal">4</flags>
        <line type="decimal">4</line>
        <column type="decimal">76</column>
        <length type="decimal">30</length>
        <window type="decimal">0</window>
        <attribute NullValue="1" type="decimal"/>
        <graph sctype="array"/>
        <input type="string">assign.date</input>
        <output NullValue="1" type="string"/>
        <format NullValue="1" type="string"/>
        <property type="string">Text;Height=2	Name=	ReadOnly=1	Width=59			X=151	Y=7		Input=assign.date	</property>
      </field>
      <field sctype="structure">
        <flags type="decimal">0</flags>
        <line type="decimal">5</line>
        <column type="decimal">1</column>
        <length type="decimal">23</length>
        <window type="decimal">0</window>
        <attribute NullValue="1" type="decimal"/>
        <graph sctype="array"/>
        <input NullValue="1" type="string"/>
        <output type="string">Reason for Change</output>
        <format NullValue="1" type="string"/>
        <property type="string">Label;Caption=Reason for Change	Justification=1	ForeColor=0	Height=2	Name=	Width=45			X=0	Y=9		</property>
      </field>
      <field sctype="structure">
        <flags type="decimal">0</flags>
        <line type="decimal">5</line>
        <column type="decimal">24</column>
        <length type="decimal">30</length>
        <window type="decimal">1</window>
        <attribute NullValue="1" type="decimal"/>
        <graph sctype="array"/>
        <input type="string">reason</input>
        <output NullValue="1" type="string"/>
        <format NullValue="1" type="string"/>
        <property type="string">ComboBox;BoxLines=4	ArrayLength=1	Height=2	Name=	Mandatory=1	SelectOnly=1	Width=59			X=46	Y=9		Input=reason	DisplayList=$G.km.reasons.desc	ValueList=$G.km.reasons	</property>
      </field>
      <field sctype="structure">
        <flags type="decimal">0</flags>
        <line type="decimal">6</line>
        <column type="decimal">59</column>
        <length type="decimal">17</length>
        <window type="decimal">0</window>
        <attribute NullValue="1" type="decimal"/>
        <graph sctype="array"/>
        <input NullValue="1" type="string"/>
        <output type="string">Change Owner</output>
        <format NullValue="1" type="string"/>
        <property type="string">Label;Caption=Change Owner	Justification=1	ForeColor=0	Height=2	Name=	Width=33			X=117	Y=11		</property>
      </field>
      <field sctype="structure">
        <flags type="decimal">0</flags>
        <line type="decimal">6</line>
        <column type="decimal">76</column>
        <length type="decimal">30</length>
        <window type="decimal">1</window>
        <attribute NullValue="1" type="decimal"/>
        <graph sctype="array"/>
        <input type="string">coordinator</input>
        <output NullValue="1" type="string"/>
        <format NullValue="1" type="string"/>
        <property type="string">ComFill;ArrayLength=1	autocomplete=1	Height=2	Name=	FillButtonID=107	ThirdButtonID=10	ReadOnly=0	ComboButtonVisible=0	FillButtonVisible=1	ThirdButtonVisible=0	SelectOnly=1	Width=59			X=151	Y=11		Input=coordinator	</property>
      </field>
      <field sctype="structure">
        <flags type="decimal">0</flags>
        <line type="decimal">7</line>
        <column type="decimal">1</column>
        <length type="decimal">23</length>
        <window type="decimal">0</window>
        <attribute NullValue="1" type="decimal"/>
        <graph sctype="array"/>
        <input NullValue="1" type="string"/>
        <output type="string">Alert Stage</output>
        <format NullValue="1" type="string"/>
        <property type="string">Label;Caption=Alert Stage	Justification=1	ForeColor=0	Height=2	Name=	Width=45			X=0	Y=13		</property>
      </field>
      <field sctype="structure">
        <flags type="decimal">4</flags>
        <line type="decimal">7</line>
        <column type="decimal">24</column>
        <length type="decimal">30</length>
        <window type="decimal">0</window>
        <attribute NullValue="1" type="decimal"/>
        <graph sctype="array"/>
        <input type="string">alert.stage</input>
        <output NullValue="1" type="string"/>
        <format NullValue="1" type="string"/>
        <property type="string">ComFill;dataType=string	Height=2	Name=	FillButtonID=9	ThirdButtonID=8	ReadOnly=1	ComboButtonVisible=0	ThirdButtonVisible=0	TabStop=	Width=59			X=46	Y=13		Input=alert.stage	</property>
      </field>
      <field sctype="structure">
        <flags type="decimal">0</flags>
        <line type="decimal">7</line>
        <column type="decimal">59</column>
        <length type="decimal">17</length>
        <window type="decimal">0</window>
        <attribute NullValue="1" type="decimal"/>
        <graph sctype="array"/>
        <input NullValue="1" type="string"/>
        <output type="string">Phone</output>
        <format NullValue="1" type="string"/>
        <property type="string">Label;Caption=Phone	Justification=1	ForeColor=0	Height=2	Name=	Width=33			X=117	Y=13		</property>
      </field>
      <field sctype="structure">
        <flags type="decimal">0</flags>
        <line type="decimal">7</line>
        <column type="decimal">76</column>
        <length type="decimal">30</length>
        <window type="decimal">0</window>
        <attribute NullValue="1" type="decimal"/>
        <graph sctype="array"/>
        <input type="string">coord.phone</input>
        <output NullValue="1" type="string"/>
        <format NullValue="1" type="string"/>
        <property type="string">Text;Height=2	Name=	Width=59			X=151	Y=13		Input=coord.phone	</property>
      </field>
      <field sctype="structure">
        <flags type="decimal">0</flags>
        <line type="decimal">8</line>
        <column type="decimal">1</column>
        <length type="decimal">23</length>
        <window type="decimal">0</window>
        <attribute NullValue="1" type="decimal"/>
        <graph sctype="array"/>
        <input NullValue="1" type="string"/>
        <output type="string">Planned Start</output>
        <format NullValue="1" type="string"/>
        <property type="string">Label;Caption=Planned Start	Justification=1	Height=2	Name=	Width=45			X=0	Y=15		</property>
      </field>
      <field sctype="structure">
        <flags type="decimal">4096</flags>
        <line type="decimal">8</line>
        <column type="decimal">24</column>
        <length type="decimal">30</length>
        <window type="decimal">1</window>
        <attribute NullValue="1" type="decimal"/>
        <graph sctype="array"/>
        <input type="string">planned.start</input>
        <output NullValue="1" type="string"/>
        <format NullValue="1" type="string"/>
        <property type="string">DateTime;Height=2	Name=	Mandatory=0	TabStop=	Width=59			X=46	Y=15		Input=planned.start	</property>
      </field>
      <field sctype="structure">
        <flags type="decimal">0</flags>
        <line type="decimal">8</line>
        <column type="decimal">59</column>
        <length type="decimal">17</length>
        <window type="decimal">0</window>
        <attribute NullValue="1" type="decimal"/>
        <graph sctype="array"/>
        <input NullValue="1" type="string"/>
        <output type="string">Date</output>
        <format NullValue="1" type="string"/>
        <property type="string">Label;Caption=Date	Justification=1	ForeColor=0	Height=2	Name=	Width=33			X=117	Y=15		</property>
      </field>
      <field sctype="structure">
        <flags type="decimal">4</flags>
        <line type="decimal">8</line>
        <column type="decimal">76</column>
        <length type="decimal">30</length>
        <window type="decimal">0</window>
        <attribute NullValue="1" type="decimal"/>
        <graph sctype="array"/>
        <input type="string">coord.date</input>
        <output NullValue="1" type="string"/>
        <format NullValue="1" type="string"/>
        <property type="string">Text;AccessibleName=	?Caption=	Height=2	Name=	ReadOnly=1	Width=59			X=151	Y=15		Input=coord.date	</property>
      </field>
      <field sctype="structure">
        <flags type="decimal">0</flags>
        <line type="decimal">9</line>
        <column type="decimal">1</column>
        <length type="decimal">23</length>
        <window type="decimal">0</window>
        <attribute NullValue="1" type="decimal"/>
        <graph sctype="array"/>
        <input NullValue="1" type="string"/>
        <output type="string">Planned End</output>
        <format NullValue="1" type="string"/>
        <property type="string">Label;Caption=Planned End	Justification=1	Height=2	Name=	Width=45			X=0	Y=17		</property>
      </field>
      <field sctype="structure">
        <flags type="decimal">4096</flags>
        <line type="decimal">9</line>
        <column type="decimal">24</column>
        <length type="decimal">30</length>
        <window type="decimal">1</window>
        <attribute NullValue="1" type="decimal"/>
        <graph sctype="array"/>
        <input type="string">planned.end</input>
        <output NullValue="1" type="string"/>
        <format NullValue="1" type="string"/>
        <property type="string">DateTime;Height=2	Name=	Mandatory=0	TabStop=	Width=59			X=46	Y=17		Input=planned.end	</property>
      </field>
      <field sctype="structure">
        <flags type="decimal">0</flags>
        <line type="decimal">10</line>
        <column type="decimal">59</column>
        <length type="decimal">17</length>
        <window type="decimal">0</window>
        <attribute NullValue="1" type="decimal"/>
        <graph sctype="array"/>
        <input NullValue="1" type="string"/>
        <output type="string">Initiated By</output>
        <format NullValue="1" type="string"/>
        <property type="string">Label;Caption=Initiated By	Justification=1	ForeColor=0	Height=2	Name=	Width=33			X=117	Y=19		</property>
      </field>
      <field sctype="structure">
        <flags type="decimal">0</flags>
        <line type="decimal">10</line>
        <column type="decimal">76</column>
        <length type="decimal">30</length>
        <window type="decimal">1</window>
        <attribute NullValue="1" type="decimal"/>
        <graph sctype="array"/>
        <input type="string">requested.by</input>
        <output NullValue="1" type="string"/>
        <format NullValue="1" type="string"/>
        <property type="string">ComFill;ArrayLength=1	autocomplete=1	Height=2	Name=	FillButtonID=9	ThirdButtonID=8	ComboButtonVisible=0	Width=59			X=151	Y=19		Input=requested.by	</property>
      </field>
      <field sctype="structure">
        <flags type="decimal">0</flags>
        <line type="decimal">11</line>
        <column type="decimal">59</column>
        <length type="decimal">17</length>
        <window type="decimal">0</window>
        <attribute NullValue="1" type="decimal"/>
        <graph sctype="array"/>
        <input NullValue="1" type="string"/>
        <output type="string">Department</output>
        <format NullValue="1" type="string"/>
        <property type="string">Label;Caption=Department	Justification=1	ForeColor=0	Height=2	Name=	Width=33			X=117	Y=21		</property>
      </field>
      <field sctype="structure">
        <flags type="decimal">0</flags>
        <line type="decimal">11</line>
        <column type="decimal">76</column>
        <length type="decimal">30</length>
        <window type="decimal">0</window>
        <attribute NullValue="1" type="decimal"/>
        <graph sctype="array"/>
        <input type="string">request.dept</input>
        <output NullValue="1" type="string"/>
        <format NullValue="1" type="string"/>
        <property type="string">Text;Height=2	Name=	Width=59			X=151	Y=21		Input=request.dept	</property>
      </field>
      <field sctype="structure">
        <flags type="decimal">0</flags>
        <line type="decimal">12</line>
        <column type="decimal">59</column>
        <length type="decimal">17</length>
        <window type="decimal">0</window>
        <attribute NullValue="1" type="decimal"/>
        <graph sctype="array"/>
        <input NullValue="1" type="string"/>
        <output type="string">Phone</output>
        <format NullValue="1" type="string"/>
        <property type="string">Label;Caption=Phone	Justification=1	ForeColor=0	Height=2	Name=	Width=33			X=117	Y=23		</property>
      </field>
      <field sctype="structure">
        <flags type="decimal">0</flags>
        <line type="decimal">12</line>
        <column type="decimal">76</column>
        <length type="decimal">30</length>
        <window type="decimal">0</window>
        <attribute NullValue="1" type="decimal"/>
        <graph sctype="array"/>
        <input type="string">request.phone</input>
        <output NullValue="1" type="string"/>
        <format NullValue="1" type="string"/>
        <property type="string">Text;Height=2	Name=	Width=59			X=151	Y=23		Input=request.phone	</property>
      </field>
      <field sctype="structure">
        <flags type="decimal">0</flags>
        <line type="decimal">13</line>
        <column type="decimal">59</column>
        <length type="decimal">17</length>
        <window type="decimal">0</window>
        <attribute NullValue="1" type="decimal"/>
        <graph sctype="array"/>
        <input NullValue="1" type="string"/>
        <output type="string">Initiated On</output>
        <format NullValue="1" type="string"/>
        <property type="string">Label;Caption=Initiated On	Justification=1	ForeColor=0	Height=2	Name=	Width=33			X=117	Y=25		</property>
      </field>
      <field sctype="structure">
        <flags type="decimal">0</flags>
        <line type="decimal">13</line>
        <column type="decimal">76</column>
        <length type="decimal">30</length>
        <window type="decimal">1</window>
        <attribute NullValue="1" type="decimal"/>
        <graph sctype="array"/>
        <input type="string">orig.date.entered</input>
        <output NullValue="1" type="string"/>
        <format NullValue="1" type="string"/>
        <property type="string">ComFill;ArrayLength=1	autocomplete=1	Height=2	Name=	FillButtonID=9	ThirdButtonID=8	ComboButtonVisible=0	Width=59			X=151	Y=25		Input=orig.date.entered	</property>
      </field>
      <field sctype="structure">
        <flags type="decimal">0</flags>
        <line type="decimal">15</line>
        <column type="decimal">59</column>
        <length type="decimal">17</length>
        <window type="decimal">0</window>
        <attribute NullValue="1" type="decimal"/>
        <graph sctype="array"/>
        <input NullValue="1" type="string"/>
        <output type="string">Category</output>
        <format NullValue="1" type="string"/>
        <property type="string">Label;Caption=Category	Justification=1	Height=2	Name=	Width=33			X=117	Y=29		</property>
      </field>
      <field sctype="structure">
        <flags type="decimal">4</flags>
        <line type="decimal">15</line>
        <column type="decimal">76</column>
        <length type="decimal">30</length>
        <window type="decimal">1</window>
        <attribute NullValue="1" type="decimal"/>
        <graph sctype="array"/>
        <input type="string">category</input>
        <output NullValue="1" type="string"/>
        <format NullValue="1" type="string"/>
        <property type="string">ComFill;BoxLines=5	ArrayLength=1	?ReadOnly=	Height=2	Name=	FillButtonID=9	ThirdButtonID=8	Mandatory=0	ReadOnly=1	ComboButtonVisible=0	FillButtonVisible=0	SelectOnly=1	TabStop=	Visible=1	Width=59			X=151	Y=29		Input=category	DisplayList=$G.cm3r.category.local	ValueList=$G.cm3r.category	</property>
      </field>
      <field sctype="structure">
        <flags type="decimal">0</flags>
        <line type="decimal">16</line>
        <column type="decimal">59</column>
        <length type="decimal">17</length>
        <window type="decimal">0</window>
        <attribute NullValue="1" type="decimal"/>
        <graph sctype="array"/>
        <input NullValue="1" type="string"/>
        <output type="string">Impact Assessment</output>
        <format NullValue="1" type="string"/>
        <property type="string">Label;Caption=Impact Assessment	Justification=1	ForeColor=0	Height=2	Name=	Width=33			X=117	Y=31		</property>
      </field>
      <field sctype="structure">
        <flags type="decimal">0</flags>
        <line type="decimal">16</line>
        <column type="decimal">76</column>
        <length type="decimal">30</length>
        <window type="decimal">1</window>
        <attribute NullValue="1" type="decimal"/>
        <graph sctype="array"/>
        <input type="string">initial.impact</input>
        <output NullValue="1" type="string"/>
        <format NullValue="1" type="string"/>
        <property type="string">ComFill;BoxLines=5	ArrayLength=1	?Visible=	Height=2	Name=	FillButtonID=9	ThirdButtonID=8	Mandatory=1	FillButtonVisible=0	SelectOnly=1	TabStop=	Width=59			X=151	Y=31		Input=initial.impact	DisplayList=$G.init.impact.disp	ValueList=$G.init.impact	</property>
      </field>
      <field sctype="structure">
        <flags type="decimal">0</flags>
        <line type="decimal">17</line>
        <column type="decimal">59</column>
        <length type="decimal">17</length>
        <window type="decimal">0</window>
        <attribute NullValue="1" type="decimal"/>
        <graph sctype="array"/>
        <input NullValue="1" type="string"/>
        <output type="string">Urgency</output>
        <format NullValue="1" type="string"/>
        <property type="string">Label;Caption=Urgency	Justification=1	ForeColor=0	Height=2	Name=	Width=33			X=117	Y=33		</property>
      </field>
      <field sctype="structure">
        <flags type="decimal">0</flags>
        <line type="decimal">17</line>
        <column type="decimal">76</column>
        <length type="decimal">30</length>
        <window type="decimal">1</window>
        <attribute NullValue="1" type="decimal"/>
        <graph sctype="array"/>
        <input type="string">severity</input>
        <output NullValue="1" type="string"/>
        <format NullValue="1" type="string"/>
        <property type="string">ComFill;BoxLines=5	ArrayLength=1	?Visible=	Height=2	Name=	FillButtonID=9	ThirdButtonID=8	Mandatory=1	FillButtonVisible=0	SelectOnly=1	TabStop=	Width=59			X=151	Y=33		Input=severity	DisplayList=$G.urgency.disp	ValueList=$G.urgency	</property>
      </field>
      <field sctype="structure">
        <flags type="decimal">0</flags>
        <line type="decimal">18</line>
        <column type="decimal">59</column>
        <length type="decimal">17</length>
        <window type="decimal">0</window>
        <attribute NullValue="1" type="decimal"/>
        <graph sctype="array"/>
        <input NullValue="1" type="string"/>
        <output type="string">Priority</output>
        <format NullValue="1" type="string"/>
        <property type="string">Label;Caption=Priority	Justification=1	?Visible=	ForeColor=0	Height=2	Name=	Width=33			X=117	Y=35		</property>
      </field>
      <field sctype="structure">
        <flags type="decimal">4</flags>
        <line type="decimal">18</line>
        <column type="decimal">76</column>
        <length type="decimal">30</length>
        <window type="decimal">1</window>
        <attribute NullValue="1" type="decimal"/>
        <graph sctype="array"/>
        <input type="string">priority.code</input>
        <output NullValue="1" type="string"/>
        <format NullValue="1" type="string"/>
        <property type="string">ComFill;ArrayLength=1	?DisplayList=	?Visible=	Height=2	Name=	FillButtonID=9	ThirdButtonID=8	ReadOnly=1	ComboButtonVisible=0	FillButtonVisible=0	TabStop=	Width=59			X=151	Y=35		Input=priority.code	DisplayList=$G.calc.priority.disp	ValueList=$G.calc.priority	</property>
      </field>
      <field sctype="structure">
        <flags type="decimal">0</flags>
        <line type="decimal">19</line>
        <column type="decimal">1</column>
        <length type="decimal">23</length>
        <window type="decimal">0</window>
        <attribute NullValue="1" type="decimal"/>
        <graph sctype="array"/>
        <input NullValue="1" type="string"/>
        <output type="string">Completion Code</output>
        <format NullValue="1" type="string"/>
        <property type="string">Label;Caption=Completion Code	Justification=1	?Caption=	ForeColor=0	Height=2	Name=	Width=45			X=0	Y=37		</property>
      </field>
      <field sctype="structure">
        <flags type="decimal">0</flags>
        <line type="decimal">19</line>
        <column type="decimal">24</column>
        <length type="decimal">30</length>
        <window type="decimal">1</window>
        <attribute NullValue="1" type="decimal"/>
        <graph sctype="array"/>
        <input type="string">completion.code</input>
        <output NullValue="1" type="string"/>
        <format NullValue="1" type="string"/>
        <property type="string">ComboBox;ArrayLength=1	?Mandatory=[status]="terminated" | [status]="closed"	?Visible=	Height=2	Name=	Width=59			X=46	Y=37		Input=completion.code	DisplayList=$G.cm.km.close.codes.desc	ValueList=$G.cm.km.close.codes	</property>
      </field>
      <field sctype="structure">
        <flags type="decimal">0</flags>
        <line type="decimal">20</line>
        <column type="decimal">1</column>
        <length type="decimal">23</length>
        <window type="decimal">0</window>
        <attribute NullValue="1" type="decimal"/>
        <graph sctype="array"/>
        <input NullValue="1" type="string"/>
        <output type="string">Description</output>
        <format NullValue="1" type="string"/>
        <property type="string">Label;Caption=Description	Justification=1	?Visible=	ForeColor=0	Height=2	Name=	Width=45			X=0	Y=39		</property>
      </field>
      <field sctype="structure">
        <flags type="decimal">512</flags>
        <line type="decimal">20</line>
        <column type="decimal">24</column>
        <length type="decimal">82</length>
        <window type="decimal">4</window>
        <attribute NullValue="1" type="decimal"/>
        <graph sctype="array"/>
        <input type="string">description</input>
        <output NullValue="1" type="string"/>
        <format NullValue="1" type="string"/>
        <property type="string">MultiText;?Mandatory=[status]="terminated" | [status]="closed"	?Visible=	Height=8	Name=	ReadOnly=0	Width=164			X=46	Y=39		Input=description	</property>
      </field>
      <field sctype="structure">
        <flags type="decimal">4096</flags>
        <line type="decimal">25</line>
        <column type="decimal">1</column>
        <length type="decimal">114</length>
        <window type="decimal">23</window>
        <attribute NullValue="1" type="decimal"/>
        <graph sctype="array"/>
        <input NullValue="1" type="string"/>
        <output type="string">VO</output>
        <format NullValue="1" type="string"/>
        <property type="string">NoteBook;?Visible=	headingLevel=h2	Height=45	Name=	lockRenderingStyle=0	scElastic=both	Visible=1	Width=227	X=0	Y=49		</property>
      </field>
      <field sctype="structure">
        <flags type="decimal">4096</flags>
        <line type="decimal">6</line>
        <column type="decimal">6</column>
        <length type="decimal">1</length>
        <window type="decimal">0</window>
        <attribute NullValue="1" type="decimal"/>
        <graph sctype="array"/>
        <input NullValue="1" type="string"/>
        <output type="string">Workflow</output>
        <format NullValue="1" type="string"/>
        <property type="string">page;?Caption=	Name=	isExpanded=1	X=10	Y=10	Caption=Workflow		</property>
      </field>
      <field sctype="structure">
        <flags type="decimal">0</flags>
        <line type="decimal">1</line>
        <column type="decimal">1</column>
        <length type="decimal">118</length>
        <window type="decimal">15</window>
        <attribute NullValue="1" type="decimal"/>
        <graph sctype="array"/>
        <input NullValue="1" type="string"/>
        <output type="string">VO</output>
        <format type="string">chm.cm3r.sub.workflow.g</format>
        <property type="string">SubFormat;Elastic=3	ArrayLength=16	Height=30	Name=	scElastic=both	Format=chm.cm3r.sub.workflow.g	Width=236	X=0	Y=0		</property>
      </field>
      <field sctype="structure">
        <flags type="decimal">4096</flags>
        <line type="decimal">1</line>
        <column type="decimal">1</column>
        <length type="decimal">1</length>
        <window type="decimal">1</window>
        <attribute NullValue="1" type="decimal"/>
        <graph sctype="array"/>
        <input NullValue="1" type="string"/>
        <output type="string">VO</output>
        <format NullValue="1" type="string"/>
        <property type="string">end;X=1	Y=1	Height=2	Width=2	</property>
      </field>
      <field sctype="structure">
        <flags type="decimal">4096</flags>
        <line type="decimal">6</line>
        <column type="decimal">6</column>
        <length type="decimal">1</length>
        <window type="decimal">0</window>
        <attribute NullValue="1" type="decimal"/>
        <graph sctype="array"/>
        <input NullValue="1" type="string"/>
        <output type="string">KM Document</output>
        <format NullValue="1" type="string"/>
        <property type="string">page;Name=page1362020577766	?Caption=	?Visible=[$L.isexternalchange]&lt;&gt;""	Name=page1362020577766	X=10	Y=10	Caption=KM Document		</property>
      </field>
      <field sctype="structure">
        <flags type="decimal">4096</flags>
        <line type="decimal">1</line>
        <column type="decimal">1</column>
        <length type="decimal">112</length>
        <window type="decimal">7</window>
        <attribute NullValue="1" type="decimal"/>
        <graph sctype="array"/>
        <input type="string">$L.docwithview</input>
        <output NullValue="1" type="string"/>
        <format NullValue="1" type="string"/>
        <property type="string">htmlViewer;AccessibleDescription=KM Document	?Visible=[$L.isexternalchange]=true	Height=13	Name=	Visible=1	Width=224	X=0	Y=0		Input=$L.docwithview	</property>
      </field>
      <field sctype="structure">
        <flags type="decimal">4096</flags>
        <line type="decimal">1</line>
        <column type="decimal">1</column>
        <length type="decimal">112</length>
        <window type="decimal">12</window>
        <attribute NullValue="1" type="decimal"/>
        <graph sctype="array"/>
        <input type="string">$L.docwithview</input>
        <output NullValue="1" type="string"/>
        <format NullValue="1" type="string"/>
        <property type="string">htmlViewer;AccessibleDescription=KM Document	?Visible=[$L.isexternalchange]=false	Height=24	Name=	Width=224	X=0	Y=0		Input=$L.docwithview	</property>
      </field>
      <field sctype="structure">
        <flags type="decimal">4096</flags>
        <line type="decimal">1</line>
        <column type="decimal">1</column>
        <length type="decimal">1</length>
        <window type="decimal">1</window>
        <attribute NullValue="1" type="decimal"/>
        <graph sctype="array"/>
        <input NullValue="1" type="string"/>
        <output type="string">VO</output>
        <format NullValue="1" type="string"/>
        <property type="string">end;X=1	Y=1	Height=2	Width=2	</property>
      </field>
      <field sctype="structure">
        <flags type="decimal">4096</flags>
        <line type="decimal">6</line>
        <column type="decimal">6</column>
        <length type="decimal">1</length>
        <window type="decimal">0</window>
        <attribute NullValue="1" type="decimal"/>
        <graph sctype="array"/>
        <input NullValue="1" type="string"/>
        <output type="string">Close Info</output>
        <format NullValue="1" type="string"/>
        <property type="string">page;Name=page1362020647242	?Visible=[open]=false	Name=page1362020647242	X=10	Y=10	Caption=Close Info		</property>
      </field>
      <field sctype="structure">
        <flags type="decimal">0</flags>
        <line type="decimal">1</line>
        <column type="decimal">1</column>
        <length type="decimal">23</length>
        <window type="decimal">0</window>
        <attribute NullValue="1" type="decimal"/>
        <graph sctype="array"/>
        <input NullValue="1" type="string"/>
        <output type="string">Completion Code</output>
        <format NullValue="1" type="string"/>
        <property type="string">Label;Caption=Completion Code	Justification=1	ForeColor=0	Height=2	Name=	Width=45	X=0	Y=1		</property>
      </field>
      <field sctype="structure">
        <flags type="decimal">0</flags>
        <line type="decimal">1</line>
        <column type="decimal">24</column>
        <length type="decimal">30</length>
        <window type="decimal">1</window>
        <attribute NullValue="1" type="decimal"/>
        <graph sctype="array"/>
        <input type="string">completion.code</input>
        <output NullValue="1" type="string"/>
        <format NullValue="1" type="string"/>
        <property type="string">ComboBox;ArrayLength=1	Height=2	Name=	Width=59	X=46	Y=1		Input=completion.code	DisplayList=$G.cm.km.close.codes.desc	ValueList=$G.cm.km.close.codes	</property>
      </field>
      <field sctype="structure">
        <flags type="decimal">0</flags>
        <line type="decimal">1</line>
        <column type="decimal">55</column>
        <length type="decimal">3</length>
        <window type="decimal">0</window>
        <attribute NullValue="1" type="decimal"/>
        <graph sctype="array"/>
        <input type="string">open</input>
        <output NullValue="1" type="string"/>
        <format NullValue="1" type="string"/>
        <property type="string">Label;ForeColor=0	Height=2	Name=	Visible=0	Width=5	X=108	Y=1		Input=open	</property>
      </field>
      <field sctype="structure">
        <flags type="decimal">0</flags>
        <line type="decimal">1</line>
        <column type="decimal">59</column>
        <length type="decimal">17</length>
        <window type="decimal">0</window>
        <attribute NullValue="1" type="decimal"/>
        <graph sctype="array"/>
        <input NullValue="1" type="string"/>
        <output type="string">Hours Worked</output>
        <format NullValue="1" type="string"/>
        <property type="string">Label;Caption=Hours Worked	ForeColor=0	Height=2	Name=	Width=33	X=117	Y=1		</property>
      </field>
      <field sctype="structure">
        <flags type="decimal">0</flags>
        <line type="decimal">1</line>
        <column type="decimal">76</column>
        <length type="decimal">30</length>
        <window type="decimal">0</window>
        <attribute NullValue="1" type="decimal"/>
        <graph sctype="array"/>
        <input type="string">hours.worked</input>
        <output NullValue="1" type="string"/>
        <format NullValue="1" type="string"/>
        <property type="string">Text;Height=2	Name=	MaxChars=14	Width=59	X=151	Y=1		Input=hours.worked	</property>
      </field>
      <field sctype="structure">
        <flags type="decimal">0</flags>
        <line type="decimal">2</line>
        <column type="decimal">1</column>
        <length type="decimal">23</length>
        <window type="decimal">0</window>
        <attribute NullValue="1" type="decimal"/>
        <graph sctype="array"/>
        <input NullValue="1" type="string"/>
        <output type="string">Closing Comments</output>
        <format NullValue="1" type="string"/>
        <property type="string">Label;Caption=Closing Comments	Justification=1	ForeColor=0	Height=2	Name=	Width=45	X=0	Y=3		</property>
      </field>
      <field sctype="structure">
        <flags type="decimal">512</flags>
        <line type="decimal">2</line>
        <column type="decimal">24</column>
        <length type="decimal">81</length>
        <window type="decimal">4</window>
        <attribute NullValue="1" type="decimal"/>
        <graph sctype="array"/>
        <input type="string">closing.comments</input>
        <output NullValue="1" type="string"/>
        <format NullValue="1" type="string"/>
        <property type="string">MultiText;Elastic=3	Height=7	Name=	Width=161	X=46	Y=3		Input=closing.comments	</property>
      </field>
      <field sctype="structure">
        <flags type="decimal">4096</flags>
        <line type="decimal">1</line>
        <column type="decimal">1</column>
        <length type="decimal">1</length>
        <window type="decimal">1</window>
        <attribute NullValue="1" type="decimal"/>
        <graph sctype="array"/>
        <input NullValue="1" type="string"/>
        <output type="string">VO</output>
        <format NullValue="1" type="string"/>
        <property type="string">end;X=1	Y=1	Height=2	Width=2	</property>
      </field>
      <field sctype="structure">
        <flags type="decimal">4096</flags>
        <line type="decimal">6</line>
        <column type="decimal">6</column>
        <length type="decimal">1</length>
        <window type="decimal">0</window>
        <attribute NullValue="1" type="decimal"/>
        <graph sctype="array"/>
        <input NullValue="1" type="string"/>
        <output type="string">Tasks</output>
        <format NullValue="1" type="string"/>
        <property type="string">page;Name=	X=10	Y=10	Caption=Tasks		</property>
      </field>
      <field sctype="structure">
        <flags type="decimal">68</flags>
        <line type="decimal">1</line>
        <column type="decimal">3</column>
        <length type="decimal">82</length>
        <window type="decimal">6</window>
        <attribute NullValue="1" type="decimal"/>
        <graph sctype="array"/>
        <input type="string">number</input>
        <output NullValue="1" type="string"/>
        <format type="string">chm.cm3r.tasks.horz</format>
        <property type="string">SubFormat;DisplayBlank=0	DisplayUsingTable=1	VirtualJoin=1	ArrayLength=15	Height=12	Name=	ReadOnly=1	scElastic=both	Format=chm.cm3r.tasks.horz	Width=164	X=5	Y=0		Input=number	</property>
      </field>
      <field sctype="structure">
        <flags type="decimal">4096</flags>
        <line type="decimal">1</line>
        <column type="decimal">1</column>
        <length type="decimal">1</length>
        <window type="decimal">1</window>
        <attribute NullValue="1" type="decimal"/>
        <graph sctype="array"/>
        <input NullValue="1" type="string"/>
        <output type="string">VO</output>
        <format NullValue="1" type="string"/>
        <property type="string">end;X=1	Y=1	Height=2	Width=2	</property>
      </field>
      <field sctype="structure">
        <flags type="decimal">4096</flags>
        <line type="decimal">6</line>
        <column type="decimal">6</column>
        <length type="decimal">1</length>
        <window type="decimal">0</window>
        <attribute NullValue="1" type="decimal"/>
        <graph sctype="array"/>
        <input NullValue="1" type="string"/>
        <output type="string">Feedback</output>
        <format NullValue="1" type="string"/>
        <property type="string">page;Name=page1362020805845	?Visible=	Name=page1362020805845	X=10	Y=10	Caption=Feedback		</property>
      </field>
      <field sctype="structure">
        <flags type="decimal">4096</flags>
        <line type="decimal">1</line>
        <column type="decimal">11</column>
        <length type="decimal">13</length>
        <window type="decimal">1</window>
        <attribute NullValue="1" type="decimal"/>
        <graph sctype="array"/>
        <input NullValue="1" type="string"/>
        <output type="string">Add</output>
        <format NullValue="1" type="string"/>
        <property type="string">Button;Caption=Add	ButtonID=2125	?ButtonID=	?Caption=	Height=2	Name=	Width=26	X=20	Y=1		</property>
      </field>
      <field sctype="structure">
        <flags type="decimal">4096</flags>
        <line type="decimal">1</line>
        <column type="decimal">26</column>
        <length type="decimal">13</length>
        <window type="decimal">1</window>
        <attribute NullValue="1" type="decimal"/>
        <graph sctype="array"/>
        <input NullValue="1" type="string"/>
        <output type="string">Delete</output>
        <format NullValue="1" type="string"/>
        <property type="string">Button;Caption=Delete	ButtonID=2127	?ButtonID=	?Caption=	Height=2	Name=	Width=26	X=50	Y=1		</property>
      </field>
      <field sctype="structure">
        <flags type="decimal">68</flags>
        <line type="decimal">3</line>
        <column type="decimal">11</column>
        <length type="decimal">83</length>
        <window type="decimal">4</window>
        <attribute NullValue="1" type="decimal"/>
        <graph sctype="array"/>
        <input type="string">id</input>
        <output NullValue="1" type="string"/>
        <format type="string">kmfeedback.subform</format>
        <property type="string">SubFormat;DisplayBlank=0	DisplayUsingTable=1	VirtualJoin=1	?Visible=	Height=8	Name=	ReadOnly=1	Format=kmfeedback.subform	Width=165	X=20	Y=4		Input=id	</property>
      </field>
      <field sctype="structure">
        <flags type="decimal">4096</flags>
        <line type="decimal">1</line>
        <column type="decimal">1</column>
        <length type="decimal">1</length>
        <window type="decimal">1</window>
        <attribute NullValue="1" type="decimal"/>
        <graph sctype="array"/>
        <input NullValue="1" type="string"/>
        <output type="string">VO</output>
        <format NullValue="1" type="string"/>
        <property type="string">end;X=1	Y=1	Height=2	Width=2	</property>
      </field>
      <field sctype="structure">
        <flags type="decimal">4096</flags>
        <line type="decimal">6</line>
        <column type="decimal">6</column>
        <length type="decimal">1</length>
        <window type="decimal">0</window>
        <attribute NullValue="1" type="decimal"/>
        <graph sctype="array"/>
        <input NullValue="1" type="string"/>
        <output type="string">VO</output>
        <format NullValue="1" type="string"/>
        <property type="string">page;?Caption=[$screlation.caption]	Name=	X=10	Y=10		</property>
      </field>
      <field sctype="structure">
        <flags type="decimal">0</flags>
        <line type="decimal">1</line>
        <column type="decimal">1</column>
        <length type="decimal">100</length>
        <window type="decimal">20</window>
        <attribute NullValue="1" type="decimal"/>
        <graph sctype="array"/>
        <input NullValue="1" type="string"/>
        <output type="string">VO</output>
        <format type="string">common.subform.relatedrecords</format>
        <property type="string">SubFormat;Name=subview1362986560993	?Visible=	Height=40	Name=subview1362986560993	Format=common.subform.relatedrecords	Width=200	X=1	Y=0		</property>
      </field>
      <field sctype="structure">
        <flags type="decimal">4096</flags>
        <line type="decimal">1</line>
        <column type="decimal">1</column>
        <length type="decimal">1</length>
        <window type="decimal">1</window>
        <attribute NullValue="1" type="decimal"/>
        <graph sctype="array"/>
        <input NullValue="1" type="string"/>
        <output type="string">VO</output>
        <format NullValue="1" type="string"/>
        <property type="string">end;X=1	Y=1	Height=2	Width=2	</property>
      </field>
      <field sctype="structure">
        <flags type="decimal">4096</flags>
        <line type="decimal">6</line>
        <column type="decimal">6</column>
        <length type="decimal">1</length>
        <window type="decimal">0</window>
        <attribute NullValue="1" type="decimal"/>
        <graph sctype="array"/>
        <input NullValue="1" type="string"/>
        <output type="string">Approvals</output>
        <format NullValue="1" type="string"/>
        <property type="string">page;Name=	X=10	Y=10	Caption=Approvals		</property>
      </field>
      <field sctype="structure">
        <flags type="decimal">4096</flags>
        <line type="decimal">1</line>
        <column type="decimal">1</column>
        <length type="decimal">106</length>
        <window type="decimal">0</window>
        <attribute NullValue="1" type="decimal"/>
        <graph sctype="array"/>
        <input NullValue="1" type="string"/>
        <output type="string">Current Approvals</output>
        <format NullValue="1" type="string"/>
        <property type="string">Frame;ArrayLength=0	canCollapse=1	floatGroup=1	headingLevel=h3	Height=13	Name=	isExpanded=1	Width=212	X=0	Y=0	Caption=Current Approvals		</property>
      </field>
      <field sctype="structure">
        <flags type="decimal">68</flags>
        <line type="decimal">2</line>
        <column type="decimal">24</column>
        <length type="decimal">82</length>
        <window type="decimal">5</window>
        <attribute NullValue="1" type="decimal"/>
        <graph sctype="array"/>
        <input type="string">number.vj</input>
        <output NullValue="1" type="string"/>
        <format type="string">Approval.horz.vj</format>
        <property type="string">SubFormat;DisplayBlank=0	DisplayUsingTable=1	VirtualJoin=1	ArrayLength=14	Height=10	Name=	ReadOnly=1	scElastic=both	Format=Approval.horz.vj	Width=164			X=46	Y=2		Input=number.vj	</property>
      </field>
      <field sctype="structure">
        <flags type="decimal">4096</flags>
        <line type="decimal">8</line>
        <column type="decimal">1</column>
        <length type="decimal">106</length>
        <window type="decimal">0</window>
        <attribute NullValue="1" type="decimal"/>
        <graph sctype="array"/>
        <input NullValue="1" type="string"/>
        <output type="string">Approval Log</output>
        <format NullValue="1" type="string"/>
        <property type="string">Frame;ArrayLength=0	canCollapse=1	floatGroup=1	headingLevel=h3	Height=13	Name=	isExpanded=1	Width=212	X=0	Y=14	Caption=Approval Log		</property>
      </field>
      <field sctype="structure">
        <flags type="decimal">68</flags>
        <line type="decimal">9</line>
        <column type="decimal">24</column>
        <length type="decimal">82</length>
        <window type="decimal">5</window>
        <attribute NullValue="1" type="decimal"/>
        <graph sctype="array"/>
        <input type="string">number.apprlog</input>
        <output NullValue="1" type="string"/>
        <format type="string">ApprovalLog.vj.g.horz</format>
        <property type="string">SubFormat;DisplayBlank=0	DisplayUsingTable=1	VirtualJoin=1	ArrayLength=14	?Visible=	Height=10	Name=	ReadOnly=1	scElastic=both	Format=ApprovalLog.vj.g.horz	Visible=1	Width=164			X=46	Y=16		Input=number.apprlog	</property>
      </field>
      <field sctype="structure">
        <flags type="decimal">4096</flags>
        <line type="decimal">14</line>
        <column type="decimal">1</column>
        <length type="decimal">106</length>
        <window type="decimal">0</window>
        <attribute NullValue="1" type="decimal"/>
        <graph sctype="array"/>
        <input NullValue="1" type="string"/>
        <output type="string">Pending Reviews</output>
        <format NullValue="1" type="string"/>
        <property type="string">Frame;ArrayLength=0	canCollapse=1	floatGroup=1	headingLevel=h3	Height=14	Name=	isExpanded=1	Width=212	X=0	Y=27	Caption=Pending Reviews		</property>
      </field>
      <field sctype="structure">
        <flags type="decimal">4100</flags>
        <line type="decimal">15</line>
        <column type="decimal">24</column>
        <length type="decimal">82</length>
        <window type="decimal">5</window>
        <attribute NullValue="1" type="decimal"/>
        <graph sctype="array"/>
        <input NullValue="1" type="string"/>
        <output type="string">VO</output>
        <format NullValue="1" type="string"/>
        <property type="string">Table;Columns=Reviewers	AccessibleDescription=Pending Reviews	Height=10	Name=	ReadOnly=1	scElastic=both	TabStop=	Width=164			X=46	Y=29		</property>
      </field>
      <field sctype="structure">
        <flags type="decimal">4096</flags>
        <line type="decimal">1</line>
        <column type="decimal">1</column>
        <length type="decimal">1</length>
        <window type="decimal">0</window>
        <attribute NullValue="1" type="decimal"/>
        <graph sctype="array"/>
        <input type="string">reviewer.class</input>
        <output type="string">Reviewers</output>
        <format NullValue="1" type="string"/>
        <property type="string">Column;Caption=Reviewers		=				Input=reviewer.class	Y=0	X=0	Width=1	Name=	Height=1	scType=Text		</property>
      </field>
      <field sctype="structure">
        <flags type="decimal">4096</flags>
        <line type="decimal">1</line>
        <column type="decimal">1</column>
        <length type="decimal">1</length>
        <window type="decimal">1</window>
        <attribute NullValue="1" type="decimal"/>
        <graph sctype="array"/>
        <input NullValue="1" type="string"/>
        <output type="string">VO</output>
        <format NullValue="1" type="string"/>
        <property type="string">end;X=1	Y=1	Height=2	Width=2	</property>
      </field>
      <field sctype="structure">
        <flags type="decimal">4096</flags>
        <line type="decimal">1</line>
        <column type="decimal">1</column>
        <length type="decimal">1</length>
        <window type="decimal">1</window>
        <attribute NullValue="1" type="decimal"/>
        <graph sctype="array"/>
        <input NullValue="1" type="string"/>
        <output type="string">VO</output>
        <format NullValue="1" type="string"/>
        <property type="string">end;X=1	Y=1	Height=2	Width=2	</property>
      </field>
      <field sctype="structure">
        <flags type="decimal">4096</flags>
        <line type="decimal">1</line>
        <column type="decimal">1</column>
        <length type="decimal">1</length>
        <window type="decimal">1</window>
        <attribute NullValue="1" type="decimal"/>
        <graph sctype="array"/>
        <input NullValue="1" type="string"/>
        <output type="string">VO</output>
        <format NullValue="1" type="string"/>
        <property type="string">end;X=1	Y=1	Height=2	Width=2	</property>
      </field>
      <field sctype="structure">
        <flags type="decimal">4096</flags>
        <line type="decimal">6</line>
        <column type="decimal">6</column>
        <length type="decimal">1</length>
        <window type="decimal">0</window>
        <attribute NullValue="1" type="decimal"/>
        <graph sctype="array"/>
        <input NullValue="1" type="string"/>
        <output type="string">Attachments</output>
        <format NullValue="1" type="string"/>
        <property type="string">page;Name=	X=10	Y=10	Caption=Attachments		</property>
      </field>
      <field sctype="structure">
        <flags type="decimal">4096</flags>
        <line type="decimal">1</line>
        <column type="decimal">3</column>
        <length type="decimal">82</length>
        <window type="decimal">5</window>
        <attribute NullValue="1" type="decimal"/>
        <graph sctype="array"/>
        <input type="string">number.attach</input>
        <output NullValue="1" type="string"/>
        <format NullValue="1" type="string"/>
        <property type="string">OleContainer;Height=10	Name=	Width=164	X=5	Y=1		Input=number.attach	</property>
      </field>
      <field sctype="structure">
        <flags type="decimal">4096</flags>
        <line type="decimal">1</line>
        <column type="decimal">1</column>
        <length type="decimal">1</length>
        <window type="decimal">1</window>
        <attribute NullValue="1" type="decimal"/>
        <graph sctype="array"/>
        <input NullValue="1" type="string"/>
        <output type="string">VO</output>
        <format NullValue="1" type="string"/>
        <property type="string">end;X=1	Y=1	Height=2	Width=2	</property>
      </field>
      <field sctype="structure">
        <flags type="decimal">4096</flags>
        <line type="decimal">6</line>
        <column type="decimal">6</column>
        <length type="decimal">1</length>
        <window type="decimal">0</window>
        <attribute NullValue="1" type="decimal"/>
        <graph sctype="array"/>
        <input NullValue="1" type="string"/>
        <output type="string">History</output>
        <format NullValue="1" type="string"/>
        <property type="string">page;Name=	X=10	Y=10	Caption=History		</property>
      </field>
      <field sctype="structure">
        <flags type="decimal">0</flags>
        <line type="decimal">1</line>
        <column type="decimal">1</column>
        <length type="decimal">104</length>
        <window type="decimal">6</window>
        <attribute NullValue="1" type="decimal"/>
        <graph sctype="array"/>
        <input NullValue="1" type="string"/>
        <output type="string">VO</output>
        <format type="string">chm.subform.history</format>
        <property type="string">SubFormat;Height=12	Name=	scElastic=both	Format=chm.subform.history	Width=207	X=0	Y=0		</property>
      </field>
      <field sctype="structure">
        <flags type="decimal">4096</flags>
        <line type="decimal">1</line>
        <column type="decimal">1</column>
        <length type="decimal">1</length>
        <window type="decimal">1</window>
        <attribute NullValue="1" type="decimal"/>
        <graph sctype="array"/>
        <input NullValue="1" type="string"/>
        <output type="string">VO</output>
        <format NullValue="1" type="string"/>
        <property type="string">end;X=1	Y=1	Height=2	Width=2	</property>
      </field>
      <field sctype="structure">
        <flags type="decimal">4096</flags>
        <line type="decimal">6</line>
        <column type="decimal">6</column>
        <length type="decimal">1</length>
        <window type="decimal">0</window>
        <attribute NullValue="1" type="decimal"/>
        <graph sctype="array"/>
        <input NullValue="1" type="string"/>
        <output type="string">User Options</output>
        <format NullValue="1" type="string"/>
        <property type="string">page;?Caption=	?Visible=[svc.options]&lt;&gt;NULL &amp; [svc.options]&lt;&gt;"" &amp; [svc.options]&lt;&gt;"&lt;form/&gt;"	Name=	X=10	Y=10	Caption=User Options		</property>
      </field>
      <field sctype="structure">
        <flags type="decimal">4100</flags>
        <line type="decimal">1</line>
        <column type="decimal">3</column>
        <length type="decimal">112</length>
        <window type="decimal">4</window>
        <attribute NullValue="1" type="decimal"/>
        <graph sctype="array"/>
        <input type="string">$svc.options</input>
        <output NullValue="1" type="string"/>
        <format NullValue="1" type="string"/>
        <property type="string">dynamicForm;Height=8	Name=	ReadOnly=1	Width=224	X=5	Y=1		Input=$svc.options	</property>
      </field>
      <field sctype="structure">
        <flags type="decimal">4096</flags>
        <line type="decimal">1</line>
        <column type="decimal">1</column>
        <length type="decimal">1</length>
        <window type="decimal">1</window>
        <attribute NullValue="1" type="decimal"/>
        <graph sctype="array"/>
        <input NullValue="1" type="string"/>
        <output type="string">VO</output>
        <format NullValue="1" type="string"/>
        <property type="string">end;X=1	Y=1	Height=2	Width=2	</property>
      </field>
      <field sctype="structure">
        <flags type="decimal">4096</flags>
        <line type="decimal">1</line>
        <column type="decimal">1</column>
        <length type="decimal">1</length>
        <window type="decimal">1</window>
        <attribute NullValue="1" type="decimal"/>
        <graph sctype="array"/>
        <input NullValue="1" type="string"/>
        <output type="string">VO</output>
        <format NullValue="1" type="string"/>
        <property type="string">end;X=1	Y=1	Height=2	Width=2	</property>
      </field>
    </field>
    <file.name type="string">cm3r</file.name>
    <editor type="string">falcon</editor>
    <last.update type="dateTime">05/11/16 15:23:46</last.update>
    <help.topic NullValue="1" type="string"/>
    <syslanguage type="string">en</syslanguage>
    <sysmodcount type="decimal">8</sysmodcount>
    <sysmoduser type="string">falcon</sysmoduser>
    <sysmodtime type="dateTime">05/11/16 15:23:46</sysmodtime>
    <description NullValue="1" type="string"/>
  </record>
</recordset>
