<?xml version="1.0" encoding="UTF-8" standalone="no"?>
<recordset table="format">
  <record id="syslanguage=&quot;en&quot; and name=&quot;svcSrcConfig.list.fields&quot;" recordid="en - svcSrcConfig.list.fields">
    <name mandatory="true" type="string">svcSrcConfig.list.fields</name>
    <field sctype="array">
      <field sctype="structure">
        <flags type="decimal">4100</flags>
        <line type="decimal">1</line>
        <column type="decimal">1</column>
        <length type="decimal">40</length>
        <window type="decimal">10</window>
        <attribute NullValue="1" type="decimal"/>
        <graph sctype="array"/>
        <input NullValue="1" type="string"/>
        <output type="string">VO</output>
        <format NullValue="1" type="string"/>
        <property type="string">Table;Columns=Field Label ID;Label;FieldNames;Field Type;Fields	DefaultButtonID=0	MultipleSelection=0	Name=field.table	Height=20	Name=field.table	ReadOnly=1	DoubleClickButtonID=404	DoubleClickField=$customFieldNames	MultipleSelectionField=$customFieldLabelIds	Visible=1	Width=80	X=1	Y=0		</property>
      </field>
      <field sctype="structure">
        <flags type="decimal">4096</flags>
        <line type="decimal">1</line>
        <column type="decimal">1</column>
        <length type="decimal">1</length>
        <window type="decimal">0</window>
        <attribute NullValue="1" type="decimal"/>
        <graph sctype="array"/>
        <input type="string">$customFieldLabelIds</input>
        <output type="string">Field Label ID</output>
        <format NullValue="1" type="string"/>
        <property type="string">Column;	Caption=Field Label ID	=	Column Width%=19.7				Input=$customFieldLabelIds	Y=0	X=0	Visible=0	Name=	ButtonID=column1131406929454	scType=Text		</property>
      </field>
      <field sctype="structure">
        <flags type="decimal">4096</flags>
        <line type="decimal">1</line>
        <column type="decimal">1</column>
        <length type="decimal">1</length>
        <window type="decimal">1</window>
        <attribute NullValue="1" type="decimal"/>
        <graph sctype="array"/>
        <input NullValue="1" type="string"/>
        <output type="string">VO</output>
        <format NullValue="1" type="string"/>
        <property type="string">end;X=1	Y=1	Height=2	Width=2	</property>
      </field>
      <field sctype="structure">
        <flags type="decimal">4096</flags>
        <line type="decimal">1</line>
        <column type="decimal">1</column>
        <length type="decimal">1</length>
        <window type="decimal">0</window>
        <attribute NullValue="1" type="decimal"/>
        <graph sctype="array"/>
        <input type="string">$customFieldLabels</input>
        <output type="string">Label</output>
        <format NullValue="1" type="string"/>
        <property type="string">Column;		Caption=Label		Column Width%=50			Input=$customFieldLabels	Y=0	X=0	ButtonID=column1131406950027	Name=input1131406950027	scType=Text		</property>
      </field>
      <field sctype="structure">
        <flags type="decimal">4096</flags>
        <line type="decimal">1</line>
        <column type="decimal">1</column>
        <length type="decimal">1</length>
        <window type="decimal">1</window>
        <attribute NullValue="1" type="decimal"/>
        <graph sctype="array"/>
        <input NullValue="1" type="string"/>
        <output type="string">VO</output>
        <format NullValue="1" type="string"/>
        <property type="string">end;X=1	Y=1	Height=2	Width=2	</property>
      </field>
      <field sctype="structure">
        <flags type="decimal">4096</flags>
        <line type="decimal">1</line>
        <column type="decimal">1</column>
        <length type="decimal">1</length>
        <window type="decimal">0</window>
        <attribute NullValue="1" type="decimal"/>
        <graph sctype="array"/>
        <input type="string">$customFieldTypes</input>
        <output type="string">Field Type</output>
        <format NullValue="1" type="string"/>
        <property type="string">Column;	Caption=Field Type	=	Column Width%=1				Input=$customFieldTypes	Y=0	X=0	Visible=0	Name=	ButtonID=column1131755920824	scType=Text		</property>
      </field>
      <field sctype="structure">
        <flags type="decimal">4096</flags>
        <line type="decimal">1</line>
        <column type="decimal">1</column>
        <length type="decimal">1</length>
        <window type="decimal">1</window>
        <attribute NullValue="1" type="decimal"/>
        <graph sctype="array"/>
        <input NullValue="1" type="string"/>
        <output type="string">VO</output>
        <format NullValue="1" type="string"/>
        <property type="string">end;X=1	Y=1	Height=2	Width=2	</property>
      </field>
      <field sctype="structure">
        <flags type="decimal">4096</flags>
        <line type="decimal">6</line>
        <column type="decimal">6</column>
        <length type="decimal">1</length>
        <window type="decimal">0</window>
        <attribute NullValue="1" type="decimal"/>
        <graph sctype="array"/>
        <input type="string">$customFieldCaptions</input>
        <output type="string">Field Names</output>
        <format NullValue="1" type="string"/>
        <property type="string">Column;		Caption=Field Names	=		Column Width%=50			Input=$customFieldCaptions	Y=10	X=10	?Caption=	ButtonID=column1298036133158	Name=input1298036133159	scType=Text		</property>
      </field>
      <field sctype="structure">
        <flags type="decimal">4096</flags>
        <line type="decimal">1</line>
        <column type="decimal">1</column>
        <length type="decimal">1</length>
        <window type="decimal">1</window>
        <attribute NullValue="1" type="decimal"/>
        <graph sctype="array"/>
        <input NullValue="1" type="string"/>
        <output type="string">VO</output>
        <format NullValue="1" type="string"/>
        <property type="string">end;X=1	Y=1	Height=2	Width=2	</property>
      </field>
      <field sctype="structure">
        <flags type="decimal">4096</flags>
        <line type="decimal">6</line>
        <column type="decimal">6</column>
        <length type="decimal">1</length>
        <window type="decimal">0</window>
        <attribute NullValue="1" type="decimal"/>
        <graph sctype="array"/>
        <input type="string">$customFieldNames</input>
        <output type="string">Fields</output>
        <format NullValue="1" type="string"/>
        <property type="string">Column;		Caption=Fields		Column Width%=16.7				Input=$customFieldNames	Y=10	X=10	Visible=0	ButtonID=column1298038407347	Name=input1298038407348	scType=Text		</property>
      </field>
      <field sctype="structure">
        <flags type="decimal">4096</flags>
        <line type="decimal">1</line>
        <column type="decimal">1</column>
        <length type="decimal">1</length>
        <window type="decimal">1</window>
        <attribute NullValue="1" type="decimal"/>
        <graph sctype="array"/>
        <input NullValue="1" type="string"/>
        <output type="string">VO</output>
        <format NullValue="1" type="string"/>
        <property type="string">end;X=1	Y=1	Height=2	Width=2	</property>
      </field>
      <field sctype="structure">
        <flags type="decimal">4096</flags>
        <line type="decimal">1</line>
        <column type="decimal">1</column>
        <length type="decimal">1</length>
        <window type="decimal">1</window>
        <attribute NullValue="1" type="decimal"/>
        <graph sctype="array"/>
        <input NullValue="1" type="string"/>
        <output type="string">VO</output>
        <format NullValue="1" type="string"/>
        <property type="string">end;X=1	Y=1	Height=2	Width=2	</property>
      </field>
      <field sctype="structure">
        <flags type="decimal">4096</flags>
        <line type="decimal">4</line>
        <column type="decimal">41</column>
        <length type="decimal">20</length>
        <window type="decimal">2</window>
        <attribute NullValue="1" type="decimal"/>
        <graph sctype="array"/>
        <input NullValue="1" type="string"/>
        <output type="string">Move Field Up</output>
        <format NullValue="1" type="string"/>
        <property type="string">Button;Caption=Move Field Up	Bitmap and Caption=true	ButtonID=407	Height=3	Name=	Bitmaps=mup	Width=40	X=80	Y=6		</property>
      </field>
      <field sctype="structure">
        <flags type="decimal">4096</flags>
        <line type="decimal">5</line>
        <column type="decimal">41</column>
        <length type="decimal">20</length>
        <window type="decimal">2</window>
        <attribute NullValue="1" type="decimal"/>
        <graph sctype="array"/>
        <input NullValue="1" type="string"/>
        <output type="string">Move Field Down</output>
        <format NullValue="1" type="string"/>
        <property type="string">Button;Caption=Move Field Down	Bitmap and Caption=true	ButtonID=408	description=	?Visible=	Height=3	Name=	Bitmaps=mdown	Width=40	X=80	Y=9		</property>
      </field>
      <field sctype="structure">
        <flags type="decimal">4096</flags>
        <line type="decimal">11</line>
        <column type="decimal">1</column>
        <length type="decimal">20</length>
        <window type="decimal">2</window>
        <attribute NullValue="1" type="decimal"/>
        <graph sctype="array"/>
        <input NullValue="1" type="string"/>
        <output type="string">Add New Custom Field</output>
        <format NullValue="1" type="string"/>
        <property type="string">Button;Caption=Add New Custom Field	Bitmap and Caption=true	ButtonID=401	Height=3	Name=	Bitmaps=tadd	Width=40	X=0	Y=20		</property>
      </field>
      <field sctype="structure">
        <flags type="decimal">4096</flags>
        <line type="decimal">11</line>
        <column type="decimal">21</column>
        <length type="decimal">17</length>
        <window type="decimal">2</window>
        <attribute NullValue="1" type="decimal"/>
        <graph sctype="array"/>
        <input NullValue="1" type="string"/>
        <output type="string">Edit Custom Field</output>
        <format NullValue="1" type="string"/>
        <property type="string">Button;Caption=Edit Custom Field	Bitmap and Caption=true	Name=button1299555044190	ButtonID=404	?ButtonID=	Height=3	Name=button1299555044190	Bitmaps=tedit	Width=34	X=40	Y=20		</property>
      </field>
      <field sctype="structure">
        <flags type="decimal">4096</flags>
        <line type="decimal">11</line>
        <column type="decimal">37</column>
        <length type="decimal">20</length>
        <window type="decimal">2</window>
        <attribute NullValue="1" type="decimal"/>
        <graph sctype="array"/>
        <input NullValue="1" type="string"/>
        <output type="string">Remove Custom Field</output>
        <format NullValue="1" type="string"/>
        <property type="string">Button;Caption=Remove Custom Field	Bitmap and Caption=true	ButtonID=402	Height=3	Name=	Bitmaps=tdelete	Width=40	X=73	Y=20		</property>
      </field>
    </field>
    <file.name NullValue="1" type="string"/>
    <editor type="string">falcon</editor>
    <last.update type="dateTime">03/07/11 13:34:31</last.update>
    <help.topic NullValue="1" type="string"/>
    <syslanguage type="string">en</syslanguage>
    <sysmodcount type="decimal">8</sysmodcount>
    <sysmoduser type="string">falcon</sysmoduser>
    <sysmodtime type="dateTime">03/07/11 19:00:31</sysmodtime>
    <description NullValue="1" type="string"/>
  </record>
</recordset>
