<?xml version="1.0" encoding="UTF-8" standalone="no"?>
<recordset table="format">
  <record id="syslanguage=&quot;en&quot; and name=&quot;patchrel.objects&quot;" recordid="en - patchrel.objects">
    <name mandatory="true" type="string">patchrel.objects</name>
    <field sctype="array">
      <field sctype="structure">
        <flags type="decimal">0</flags>
        <line type="decimal">1</line>
        <column type="decimal">3</column>
        <length type="decimal">13</length>
        <window type="decimal">0</window>
        <attribute NullValue="1" type="decimal"/>
        <graph sctype="array"/>
        <input NullValue="1" type="string"/>
        <output type="string">Name</output>
        <format NullValue="1" type="string"/>
        <property type="string">Label;Caption=Name	Name=Label0	Height=2	Name=Label0	Width=26	X=5	Y=1		</property>
      </field>
      <field sctype="structure">
        <flags type="decimal">0</flags>
        <line type="decimal">1</line>
        <column type="decimal">18</column>
        <length type="decimal">21</length>
        <window type="decimal">0</window>
        <attribute NullValue="1" type="decimal"/>
        <graph sctype="array"/>
        <input type="string">object.name</input>
        <output NullValue="1" type="string"/>
        <format NullValue="1" type="string"/>
        <property type="string">Text;Name=Text1	Height=2	Name=Text1	Width=42	X=34	Y=1		Input=object.name	</property>
      </field>
      <field sctype="structure">
        <flags type="decimal">0</flags>
        <line type="decimal">3</line>
        <column type="decimal">3</column>
        <length type="decimal">90</length>
        <window type="decimal">11</window>
        <attribute NullValue="1" type="decimal"/>
        <graph sctype="array"/>
        <input type="string">contents</input>
        <output NullValue="1" type="string"/>
        <format type="string">patchrel.objects.sub</format>
        <property type="string">SubFormat;Name=SubFormat2	?Visible=	Height=22	Name=SubFormat2	Format=patchrel.objects.sub	Width=180	X=4	Y=4		Input=contents	</property>
      </field>
    </field>
    <file.name type="string">patchrelobjects</file.name>
    <editor type="string">prietke</editor>
    <last.update type="dateTime">11/12/08 03:24:27</last.update>
    <help.topic NullValue="1" type="string"/>
    <syslanguage type="string">en</syslanguage>
    <sysmodcount type="decimal">6</sysmodcount>
    <sysmoduser type="string">falcon</sysmoduser>
    <sysmodtime type="dateTime">06/15/21 00:37:49</sysmodtime>
    <description NullValue="1" type="string"/>
  </record>
</recordset>
