<?xml version="1.0" encoding="UTF-8" standalone="no"?>
<recordset table="smpatches">
  <record id="version=&quot;SM9.70&quot; and tag=&quot;dbdict;scarea&quot;" recordid="SM9.70 - dbdict;scarea">
    <version type="string">SM9.70</version>
    <tag type="string">dbdict;scarea</tag>
    <filename type="string">dbdict</filename>
    <action type="string">update</action>
    <curr.sig type="string">2670960146</curr.sig>
    <pre.sigs sctype="array">
      <pre.sigs sctype="string">1286972786</pre.sigs>
    </pre.sigs>
    <pre.sigs.ver sctype="array">
      <pre.sigs.ver sctype="string">SM9.70.0024</pre.sigs.ver>
    </pre.sigs.ver>
    <sysmodtime type="dateTime">06/15/21 00:38:48</sysmodtime>
    <sysmoduser type="string">falcon</sysmoduser>
    <sysmodcount type="decimal">0</sysmodcount>
  </record>
</recordset>
