<?xml version="1.0" encoding="UTF-8" standalone="no"?>
<recordset table="activitycm3t">
  <record id="number=&quot;T8&quot; and negdatestamp='67727 11:32:58' and thenumber=&quot;001A10007&quot;" recordid="T8 - 67727 11:32:58 - 001A10007">
    <thenumber type="string">001A10007</thenumber>
    <number type="string">T8</number>
    <type type="string">Phase Change</type>
    <datestamp type="dateTime">07/27/14 16:27:02</datestamp>
    <operator type="string">falcon</operator>
    <description sctype="array">
      <description sctype="string">"Waiting" to "Active"</description>
    </description>
    <negdatestamp type="dateTime">67727 11:32:58</negdatestamp>
    <sysmodtime type="dateTime">10/19/14 19:14:33</sysmodtime>
    <sysmodcount type="decimal">1</sysmodcount>
    <sysmoduser type="string">falcon</sysmoduser>
    <syshomesite NullValue="1" type="decimal"/>
    <cust.visible NullValue="1" type="boolean"/>
  </record>
</recordset>
