<?xml version="1.0" encoding="UTF-8" standalone="no"?>
<recordset table="format">
  <record id="syslanguage=&quot;en&quot; and name=&quot;inbox.favorites.edit.search&quot;" recordid="en - inbox.favorites.edit.search">
    <name mandatory="true" type="string">inbox.favorites.edit.search</name>
    <field sctype="array">
      <field sctype="structure">
        <flags type="decimal">0</flags>
        <line type="decimal">1</line>
        <column type="decimal">1</column>
        <length type="decimal">78</length>
        <window type="decimal">0</window>
        <attribute type="decimal">2</attribute>
        <graph sctype="array"/>
        <input NullValue="1" type="string"/>
        <output type="string">Favorite definition</output>
        <format NullValue="1" type="string"/>
        <property type="string">Label;Caption=Favorite definition	Name=Label0	Opaque=1	BackColor=6	Bold=1	?Visible=[inbox.class]&lt;&gt;"classView"	FontIncrease=2	ForeColor=10	Height=2	Name=Label0	Elastic=1	Width=156	X=0	Y=0		</property>
      </field>
      <field sctype="structure">
        <flags type="decimal">0</flags>
        <line type="decimal">1</line>
        <column type="decimal">1</column>
        <length type="decimal">78</length>
        <window type="decimal">0</window>
        <attribute type="decimal">2</attribute>
        <graph sctype="array"/>
        <input NullValue="1" type="string"/>
        <output type="string">View Definition</output>
        <format NullValue="1" type="string"/>
        <property type="string">Label;Caption=View Definition	Opaque=1	BackColor=6	Bold=1	?Visible=[inbox.class]="classView"	FontIncrease=2	ForeColor=10	Height=2	Name=	Elastic=1	Width=156	X=0	Y=0		</property>
      </field>
      <field sctype="structure">
        <flags type="decimal">0</flags>
        <line type="decimal">2</line>
        <column type="decimal">2</column>
        <length type="decimal">17</length>
        <window type="decimal">0</window>
        <attribute type="decimal">2</attribute>
        <graph sctype="array"/>
        <input NullValue="1" type="string"/>
        <output type="string">Name:</output>
        <format NullValue="1" type="string"/>
        <property type="string">Label;Caption=Name:	Name=Label37	ForeColor=0	Height=2	Name=Label37	Width=34	X=2	Y=3		</property>
      </field>
      <field sctype="structure">
        <flags type="decimal">0</flags>
        <line type="decimal">2</line>
        <column type="decimal">19</column>
        <length type="decimal">50</length>
        <window type="decimal">0</window>
        <attribute type="decimal">1</attribute>
        <graph sctype="array"/>
        <input type="string">inbox.name</input>
        <output NullValue="1" type="string"/>
        <format NullValue="1" type="string"/>
        <property type="string">Text;Name=Text2	Height=2	Name=Text2	Width=100	X=36	Y=3		Input=inbox.name	</property>
      </field>
      <field sctype="structure">
        <flags type="decimal">0</flags>
        <line type="decimal">3</line>
        <column type="decimal">2</column>
        <length type="decimal">17</length>
        <window type="decimal">0</window>
        <attribute type="decimal">2</attribute>
        <graph sctype="array"/>
        <input NullValue="1" type="string"/>
        <output type="string">Table:</output>
        <format NullValue="1" type="string"/>
        <property type="string">Label;Caption=Table:	Name=Label33	ForeColor=0	Height=2	Name=Label33	Width=34	X=2	Y=5		</property>
      </field>
      <field sctype="structure">
        <flags type="decimal">4096</flags>
        <line type="decimal">3</line>
        <column type="decimal">19</column>
        <length type="decimal">18</length>
        <window type="decimal">1</window>
        <attribute type="decimal">2</attribute>
        <graph sctype="array"/>
        <input type="string">inbox.type</input>
        <output NullValue="1" type="string"/>
        <format NullValue="1" type="string"/>
        <property type="string">ComFill;Name=comfill1119637747432	dataType=string	?ValueList=	Height=2	Name=comfill1119637747432	FillButtonID=9	ThirdButtonID=8	ComboButtonVisible=1	ThirdButtonVisible=0	SelectOnly=0	Width=36	X=36	Y=5		Input=inbox.type	ValueList=$G.files	</property>
      </field>
      <field sctype="structure">
        <flags type="decimal">0</flags>
        <line type="decimal">4</line>
        <column type="decimal">2</column>
        <length type="decimal">17</length>
        <window type="decimal">0</window>
        <attribute type="decimal">2</attribute>
        <graph sctype="array"/>
        <input NullValue="1" type="string"/>
        <output type="string">Class:</output>
        <format NullValue="1" type="string"/>
        <property type="string">Label;Caption=Class:	ForeColor=0	Height=2	Name=	Width=34	X=2	Y=7		</property>
      </field>
      <field sctype="structure">
        <flags type="decimal">4096</flags>
        <line type="decimal">4</line>
        <column type="decimal">19</column>
        <length type="decimal">18</length>
        <window type="decimal">1</window>
        <attribute type="decimal">2</attribute>
        <graph sctype="array"/>
        <input type="string">inbox.class</input>
        <output NullValue="1" type="string"/>
        <format NullValue="1" type="string"/>
        <property type="string">ComFill;dataType=string	?DisplayList=	?ValueList=	Height=2	Name=	FillButtonID=9	ThirdButtonID=8	FillButtonVisible=0	ThirdButtonVisible=0	SelectOnly=1	Width=36	X=36	Y=7		Input=inbox.class	DisplayList=$L.classes.names.disp	ValueList=$L.classes.names	</property>
      </field>
      <field sctype="structure">
        <flags type="decimal">0</flags>
        <line type="decimal">5</line>
        <column type="decimal">2</column>
        <length type="decimal">17</length>
        <window type="decimal">0</window>
        <attribute type="decimal">2</attribute>
        <graph sctype="array"/>
        <input NullValue="1" type="string"/>
        <output type="string">View Type:</output>
        <format NullValue="1" type="string"/>
        <property type="string">Label;Caption=View Type:	?Visible=	ForeColor=0	Height=2	Name=	Width=34	X=2	Y=9		</property>
      </field>
      <field sctype="structure">
        <flags type="decimal">4096</flags>
        <line type="decimal">5</line>
        <column type="decimal">19</column>
        <length type="decimal">18</length>
        <window type="decimal">1</window>
        <attribute type="decimal">2</attribute>
        <graph sctype="array"/>
        <input type="string">viewtype</input>
        <output NullValue="1" type="string"/>
        <format NullValue="1" type="string"/>
        <property type="string">ComFill;dataType=string	?DisplayList=	?ValueList=	?Visible=	Height=2	Name=	FillButtonID=9	ThirdButtonID=8	FillButtonVisible=0	ThirdButtonVisible=0	SelectOnly=1	Width=36	X=36	Y=9		Input=viewtype	ValueList=Table	</property>
      </field>
      <field sctype="structure">
        <flags type="decimal">0</flags>
        <line type="decimal">6</line>
        <column type="decimal">2</column>
        <length type="decimal">17</length>
        <window type="decimal">0</window>
        <attribute type="decimal">2</attribute>
        <graph sctype="array"/>
        <input NullValue="1" type="string"/>
        <output type="string">Manager:</output>
        <format NullValue="1" type="string"/>
        <property type="string">Label;Caption=Manager:	Name=label1106005102356	ForeColor=0	Height=2	Name=label1106005102356	Width=34	X=2	Y=11		</property>
      </field>
      <field sctype="structure">
        <flags type="decimal">4096</flags>
        <line type="decimal">6</line>
        <column type="decimal">19</column>
        <length type="decimal">18</length>
        <window type="decimal">1</window>
        <attribute type="decimal">2</attribute>
        <graph sctype="array"/>
        <input type="string">inbox.manager</input>
        <output NullValue="1" type="string"/>
        <format NullValue="1" type="string"/>
        <property type="string">ComFill;Name=comfill1113861360184	dataType=string	Height=2	Name=comfill1113861360184	FillButtonID=9	ThirdButtonID=8	ComboButtonVisible=0	ThirdButtonVisible=0	Width=36	X=36	Y=11		Input=inbox.manager	</property>
      </field>
      <field sctype="structure">
        <flags type="decimal">0</flags>
        <line type="decimal">7</line>
        <column type="decimal">2</column>
        <length type="decimal">17</length>
        <window type="decimal">0</window>
        <attribute type="decimal">2</attribute>
        <graph sctype="array"/>
        <input NullValue="1" type="string"/>
        <output type="string">Content managers:</output>
        <format NullValue="1" type="string"/>
        <property type="string">Label;Caption=Content managers:	Name=label1105660482923	?Visible=	ForeColor=0	Height=2	Name=label1105660482923	Width=34	X=2	Y=13		</property>
      </field>
      <field sctype="structure">
        <flags type="decimal">4096</flags>
        <line type="decimal">7</line>
        <column type="decimal">19</column>
        <length type="decimal">18</length>
        <window type="decimal">2</window>
        <attribute type="decimal">2</attribute>
        <graph sctype="array"/>
        <input type="string">content.managers</input>
        <output NullValue="1" type="string"/>
        <format NullValue="1" type="string"/>
        <property type="string">ComFill;BoxLines=20	Name=comfill1113861363467	ArrayLength=2	dataType=string	?Visible=	Height=2	Name=comfill1113861363467	FillButtonID=9	ThirdButtonID=8	ComboButtonVisible=0	ThirdButtonVisible=0	Width=36	X=36	Y=13		Input=content.managers	</property>
      </field>
      <field sctype="structure">
        <flags type="decimal">4096</flags>
        <line type="decimal">9</line>
        <column type="decimal">2</column>
        <length type="decimal">40</length>
        <window type="decimal">0</window>
        <attribute type="decimal">2</attribute>
        <graph sctype="array"/>
        <input NullValue="1" type="string"/>
        <output type="string">Audience</output>
        <format NullValue="1" type="string"/>
        <property type="string">Frame;Name=fieldset1168299483207	ArrayLength=0	Height=20	Name=fieldset1168299483207	Visible=1	Width=80	X=2	Y=17	Caption=Audience		</property>
      </field>
      <field sctype="structure">
        <flags type="decimal">4096</flags>
        <line type="decimal">10</line>
        <column type="decimal">2</column>
        <length type="decimal">14</length>
        <window type="decimal">1</window>
        <attribute type="decimal">2</attribute>
        <graph sctype="array"/>
        <input type="string">audience.type</input>
        <output type="string">Selected Operator</output>
        <format NullValue="1" type="string"/>
        <property type="string">Radio;Name=Radio8	Value=oneperson	Value=oneperson	Height=1	Name=Radio8	Width=28			Caption=Selected Operator	X=3	Y=19		Input=audience.type	</property>
      </field>
      <field sctype="structure">
        <flags type="decimal">4096</flags>
        <line type="decimal">10</line>
        <column type="decimal">22</column>
        <length type="decimal">18</length>
        <window type="decimal">1</window>
        <attribute type="decimal">2</attribute>
        <graph sctype="array"/>
        <input type="string">operator.name</input>
        <output NullValue="1" type="string"/>
        <format NullValue="1" type="string"/>
        <property type="string">ComFill;Name=comfill1119637689942	dataType=string	?Visible=	Height=2	Name=comfill1119637689942	FillButtonID=9	ThirdButtonID=8	ComboButtonVisible=0	ThirdButtonVisible=0	Width=36			X=42	Y=19		Input=operator.name	</property>
      </field>
      <field sctype="structure">
        <flags type="decimal">4096</flags>
        <line type="decimal">11</line>
        <column type="decimal">2</column>
        <length type="decimal">13</length>
        <window type="decimal">1</window>
        <attribute type="decimal">2</attribute>
        <graph sctype="array"/>
        <input type="string">audience.type</input>
        <output type="string">Selected Groups</output>
        <format NullValue="1" type="string"/>
        <property type="string">Radio;Name=Radio9	Value=groups	Value=groups	Height=1	Name=Radio9	Width=26			Caption=Selected Groups	X=3	Y=21		Input=audience.type	</property>
      </field>
      <field sctype="structure">
        <flags type="decimal">4096</flags>
        <line type="decimal">11</line>
        <column type="decimal">22</column>
        <length type="decimal">18</length>
        <window type="decimal">2</window>
        <attribute type="decimal">2</attribute>
        <graph sctype="array"/>
        <input type="string">groups</input>
        <output NullValue="1" type="string"/>
        <format NullValue="1" type="string"/>
        <property type="string">ComFill;Name=comfill1119637641468	ArrayLength=2	dataType=string	?Visible=	Height=2	Name=comfill1119637641468	FillButtonID=9	ThirdButtonID=8	ComboButtonVisible=0	ThirdButtonVisible=0	Width=36			X=42	Y=21		Input=groups	</property>
      </field>
      <field sctype="structure">
        <flags type="decimal">4096</flags>
        <line type="decimal">14</line>
        <column type="decimal">2</column>
        <length type="decimal">12</length>
        <window type="decimal">1</window>
        <attribute type="decimal">2</attribute>
        <graph sctype="array"/>
        <input type="string">audience.type</input>
        <output type="string">Selected Roles</output>
        <format NullValue="1" type="string"/>
        <property type="string">Radio;Name=Radio10	Value=role	Value=role	Height=1	Name=Radio10	Width=23			Caption=Selected Roles	X=3	Y=26		Input=audience.type	</property>
      </field>
      <field sctype="structure">
        <flags type="decimal">4096</flags>
        <line type="decimal">14</line>
        <column type="decimal">22</column>
        <length type="decimal">18</length>
        <window type="decimal">2</window>
        <attribute type="decimal">2</attribute>
        <graph sctype="array"/>
        <input type="string">role</input>
        <output NullValue="1" type="string"/>
        <format NullValue="1" type="string"/>
        <property type="string">ComFill;ArrayLength=2	dataType=string	?ReadOnly=	?Visible=	Height=2	Name=	FillButtonID=9	ThirdButtonID=8	ComboButtonVisible=0	ThirdButtonVisible=0	Width=36			X=42	Y=26		Input=role	</property>
      </field>
      <field sctype="structure">
        <flags type="decimal">0</flags>
        <line type="decimal">16</line>
        <column type="decimal">21</column>
        <length type="decimal">10</length>
        <window type="decimal">0</window>
        <attribute type="decimal">2</attribute>
        <graph sctype="array"/>
        <input type="string">$L.void</input>
        <output NullValue="1" type="string"/>
        <format NullValue="1" type="string"/>
        <property type="string">Label;Name=label1168299635251	Height=2	Name=label1168299635251	Width=20			X=41	Y=30		Input=$L.void	</property>
      </field>
      <field sctype="structure">
        <flags type="decimal">4096</flags>
        <line type="decimal">16</line>
        <column type="decimal">2</column>
        <length type="decimal">10</length>
        <window type="decimal">1</window>
        <attribute type="decimal">2</attribute>
        <graph sctype="array"/>
        <input type="string">audience.type</input>
        <output type="string">Everyone</output>
        <format NullValue="1" type="string"/>
        <property type="string">Radio;Value=everyone	Value=everyone	Height=1	Name=	Width=19			Caption=Everyone	X=3	Y=31		Input=audience.type	</property>
      </field>
    </field>
    <file.name type="string">inbox</file.name>
    <editor type="string">joeh</editor>
    <last.update type="dateTime">01/16/07 06:03:00</last.update>
    <help.topic NullValue="1" type="string"/>
    <syslanguage type="string">en</syslanguage>
    <sysmodcount type="decimal">11</sysmodcount>
    <sysmoduser type="string">falcon</sysmoduser>
    <sysmodtime type="dateTime">01/18/07 02:48:59</sysmodtime>
    <description NullValue="1" type="string"/>
  </record>
</recordset>
